ezfacesys/__init__.py
ezfacesys/drill_data.py
ezfacesys/face_recognition.py
ezfacesys/face_save.py
ezfacesys-0.1.0.dist-info/LICENSE
ezfacesys-0.1.0.dist-info/METADATA
ezfacesys-0.1.0.dist-info/WHEEL
ezfacesys-0.1.0.dist-info/top_level.txt
ezfacesys-0.1.0.dist-info/RECORD
